
<!DOCTYPE suite SYSTEM "http://testng.org/testng-1.0.dtd">
<suite name="Suite 1">  <!--Tüm testleri kapsayan bölüm suit-->
    <test name="Test1">   <!-- test 1 kapsayan bölüm-->
        <classes> <!-- çalışacak sınıfların yazıldıgı bölüm-->
            <class name="TestNg4._01_Intro"></class>
            <class name="TestNg4._02_Intro"></class>
        </classes>
    </test>



    <test name="Test2">   <!-- test 1 kapsayan bölüm-->
        <classes> <!-- çalışacak sınıfların yazıldıgı bölüm-->
            <class name="TestNg4._01_Intro"></class>
            <class name="TestNg4._02_Intro"></class>
        </classes>
    </test>

</suite>